check_pfda/__init__.py
check_pfda/__main__.py
check_pfda/cli.py
check_pfda/config.yaml
check_pfda/core.py
check_pfda/utils.py
check_pfda-0.0.5.dist-info/METADATA
check_pfda-0.0.5.dist-info/WHEEL
check_pfda-0.0.5.dist-info/entry_points.txt
check_pfda-0.0.5.dist-info/top_level.txt
check_pfda-0.0.5.dist-info/RECORD
