Metadata-Version: 2.4
Name: check-pfda
Version: 0.0.5
Summary: PFDA test running package.
Requires-Python: >=3.8
Requires-Dist: click
Requires-Dist: pytest
Requires-Dist: requests
Requires-Dist: PyYAML
